foreflow/__init__.py
foreflow/cli.py
foreflow/foreflow.py
foreflow/test_foreflow.py
foreflow/test_types.py
foreflow/types.py
foreflow/util/__init__.py
foreflow/util/jmespath.py
foreflow/util/pydantic.py
foreflow/util/test_jmespath.py
foreflow-0.1.0.dist-info/LICENSE
foreflow-0.1.0.dist-info/METADATA
foreflow-0.1.0.dist-info/WHEEL
foreflow-0.1.0.dist-info/entry_points.txt
foreflow-0.1.0.dist-info/RECORD
